cli_phone_book/__init__.py
cli_phone_book/cli_parser.py
cli_phone_book/main.py
cli_phone_book-0.4.1.dist-info/licenses/LICENCE
cli_phone_book-0.4.1.dist-info/METADATA
cli_phone_book-0.4.1.dist-info/WHEEL
cli_phone_book-0.4.1.dist-info/entry_points.txt
cli_phone_book-0.4.1.dist-info/top_level.txt
cli_phone_book-0.4.1.dist-info/RECORD
