Metadata-Version: 2.4
Name: cli_phone_book
Version: 0.4.1
Summary: CLI телефонный справочник с --help.
Author-email: Anton Ivanov <antoivanov@korusconsulting.ru>
License: MIT
Classifier: Programming Language :: Python :: 3
Classifier: Operating System :: OS Independent
License-File: LICENCE
Dynamic: license-file
